[
    {
        "nama": "Syarahil Moch H.",
        "email": "syarahil@example.com",
        "pesan": "Halo, saya ingin menanyakan tentang program ketahanan pangan di Jawa Barat.",
        "tanggal": "2025-11-10 15:45:00"
    },
    {
        "nama": "Ridho",
        "email": "ridho@example.com",
        "pesan": "Apakah Dinas Pertanian menerima magang mahasiswa?",
        "tanggal": "2025-11-10 16:10:00"
    },
    {
        "nama": "Sidik",
        "email": "sidik@example.com",
        "pesan": "Mohon informasi mengenai cara mendapatkan bantuan alat pertanian.",
        "tanggal": "2025-11-10 17:00:00"
    },
    {
        "nama": "Ir. DADAN HIDAYAT, M.Si.",
        "email": "rahil@example.com",
        "pesan": "aaa",
        "tanggal": "2025-11-11 16:23:29"
    }
]